LICENSE
MANIFEST.in
README.md
requirements.txt
setup.py
lsankidb.egg-info/PKG-INFO
lsankidb.egg-info/SOURCES.txt
lsankidb.egg-info/dependency_links.txt
lsankidb.egg-info/entry_points.txt
lsankidb.egg-info/requires.txt
lsankidb.egg-info/top_level.txt
src/__init__.py
src/lsankidb.py
test/test_lsankidb.py