Metadata-Version: 1.1
Name: lsankidb
Version: 1.0.0
Summary: "ls" for your local Anki database.
Home-page: https://github.com/AurelienLourot/lsankidb
Author: Aurelien Lourot
Author-email: aurelien.lourot@gmail.com
License: public domain
Download-URL: https://github.com/AurelienLourot/lsankidb/tarball/1.0.0
Keywords: anki,terminal,cli,dump,ls
Platform: UNKNOWN
Classifier: Development Status :: 4 - Beta
Classifier: Environment :: Console
Classifier: Intended Audience :: Developers
Classifier: License :: Public Domain
Classifier: Natural Language :: English
Classifier: Operating System :: POSIX :: Linux
Classifier: Programming Language :: Python :: 3.5
Classifier: Programming Language :: Python :: 3.6
Classifier: Topic :: Education
Classifier: Topic :: Utilities
